<annotation>
	<folder>17</folder>
	<filename>1707.jpg</filename>
	<path>C:\Users\Administrator\Desktop\17\17\1707.jpg</path>
	<source>
		<database>Unknown</database>
	</source>
	<size>
		<width>960</width>
		<height>1280</height>
		<depth>3</depth>
	</size>
	<segmented>0</segmented>
	<object>
		<name>led</name>
		<pose>Unspecified</pose>
		<truncated>0</truncated>
		<difficult>0</difficult>
		<bndbox>
			<xmin>388</xmin>
			<ymin>92</ymin>
			<xmax>521</xmax>
			<ymax>423</ymax>
		</bndbox>
	</object>
	<object>
		<name>alarm</name>
		<pose>Unspecified</pose>
		<truncated>0</truncated>
		<difficult>0</difficult>
		<bndbox>
			<xmin>432</xmin>
			<ymin>696</ymin>
			<xmax>466</xmax>
			<ymax>728</ymax>
		</bndbox>
	</object>
	<object>
		<name>20</name>
		<pose>Unspecified</pose>
		<truncated>0</truncated>
		<difficult>0</difficult>
		<bndbox>
			<xmin>465</xmin>
			<ymin>781</ymin>
			<xmax>506</xmax>
			<ymax>830</ymax>
		</bndbox>
	</object>
	<object>
		<name>19</name>
		<pose>Unspecified</pose>
		<truncated>0</truncated>
		<difficult>0</difficult>
		<bndbox>
			<xmin>395</xmin>
			<ymin>776</ymin>
			<xmax>435</xmax>
			<ymax>821</ymax>
		</bndbox>
	</object>
	<object>
		<name>18</name>
		<pose>Unspecified</pose>
		<truncated>0</truncated>
		<difficult>0</difficult>
		<bndbox>
			<xmin>462</xmin>
			<ymin>840</ymin>
			<xmax>509</xmax>
			<ymax>889</ymax>
		</bndbox>
	</object>
	<object>
		<name>17</name>
		<pose>Unspecified</pose>
		<truncated>0</truncated>
		<difficult>0</difficult>
		<bndbox>
			<xmin>398</xmin>
			<ymin>831</ymin>
			<xmax>433</xmax>
			<ymax>875</ymax>
		</bndbox>
	</object>
	<object>
		<name>16</name>
		<pose>Unspecified</pose>
		<truncated>0</truncated>
		<difficult>0</difficult>
		<bndbox>
			<xmin>466</xmin>
			<ymin>901</ymin>
			<xmax>504</xmax>
			<ymax>947</ymax>
		</bndbox>
	</object>
	<object>
		<name>15</name>
		<pose>Unspecified</pose>
		<truncated>0</truncated>
		<difficult>0</difficult>
		<bndbox>
			<xmin>397</xmin>
			<ymin>889</ymin>
			<xmax>435</xmax>
			<ymax>933</ymax>
		</bndbox>
	</object>
	<object>
		<name>13</name>
		<pose>Unspecified</pose>
		<truncated>0</truncated>
		<difficult>0</difficult>
		<bndbox>
			<xmin>464</xmin>
			<ymin>958</ymin>
			<xmax>504</xmax>
			<ymax>1007</ymax>
		</bndbox>
	</object>
	<object>
		<name>12</name>
		<pose>Unspecified</pose>
		<truncated>0</truncated>
		<difficult>0</difficult>
		<bndbox>
			<xmin>397</xmin>
			<ymin>944</ymin>
			<xmax>432</xmax>
			<ymax>990</ymax>
		</bndbox>
	</object>
	<object>
		<name>11</name>
		<pose>Unspecified</pose>
		<truncated>0</truncated>
		<difficult>0</difficult>
		<bndbox>
			<xmin>464</xmin>
			<ymin>1018</ymin>
			<xmax>505</xmax>
			<ymax>1068</ymax>
		</bndbox>
	</object>
	<object>
		<name>UG</name>
		<pose>Unspecified</pose>
		<truncated>0</truncated>
		<difficult>0</difficult>
		<bndbox>
			<xmin>396</xmin>
			<ymin>1003</ymin>
			<xmax>433</xmax>
			<ymax>1047</ymax>
		</bndbox>
	</object>
	<object>
		<name>close</name>
		<pose>Unspecified</pose>
		<truncated>0</truncated>
		<difficult>0</difficult>
		<bndbox>
			<xmin>464</xmin>
			<ymin>1111</ymin>
			<xmax>504</xmax>
			<ymax>1161</ymax>
		</bndbox>
	</object>
	<object>
		<name>open</name>
		<pose>Unspecified</pose>
		<truncated>0</truncated>
		<difficult>0</difficult>
		<bndbox>
			<xmin>389</xmin>
			<ymin>1089</ymin>
			<xmax>441</xmax>
			<ymax>1143</ymax>
		</bndbox>
	</object>
</annotation>
